indipyconsole/__init__.py
indipyconsole/__main__.py
indipyconsole/choosevectorscreen.py
indipyconsole/consoleclient.py
indipyconsole/devicesscreen.py
indipyconsole/memberscreen.py
indipyconsole/vectorscreen.py
indipyconsole/widgets.py
indipyconsole/windows.py
indipyconsole/indipyclient/__init__.py
indipyconsole/indipyclient/events.py
indipyconsole/indipyclient/ipyclient.py
indipyconsole/indipyclient/propertymembers.py
indipyconsole/indipyclient/propertyvectors.py
indipyconsole/indipyclient/queclient.py
indipyconsole-0.0.3.dist-info/entry_points.txt
indipyconsole-0.0.3.dist-info/licenses/LICENSE
indipyconsole-0.0.3.dist-info/WHEEL
indipyconsole-0.0.3.dist-info/METADATA
indipyconsole-0.0.3.dist-info/RECORD
