Metadata-Version: 2.4
Name: indipyconsole
Version: 0.0.3
Summary: A terminal client which can be used to control remote instruments using the INDI protocol.
Keywords: indi,client,astronomy,instrument
Author-email: Bernard Czenkusz <bernie@skipole.co.uk>
Requires-Python: >=3.10
Classifier: License :: OSI Approved :: MIT License
Classifier: Topic :: Scientific/Engineering :: Astronomy
Classifier: Topic :: Scientific/Engineering :: Interface Engine/Protocol Translator
License-File: LICENSE
Project-URL: Source, https://github.com/bernie-skipole/indipyconsole
